lunchmoney/__init__.py
lunchmoney/categories.py
lunchmoney/client.py
lunchmoney/tags.py
lunchmoney/transactions.py
lunchmoney-0.1.0.dist-info/WHEEL
lunchmoney-0.1.0.dist-info/METADATA
lunchmoney-0.1.0.dist-info/RECORD
